cheerup/__init__.py
cheerup-0.1.5.dist-info/LICENSE
cheerup-0.1.5.dist-info/METADATA
cheerup-0.1.5.dist-info/WHEEL
cheerup-0.1.5.dist-info/entry_points.txt
cheerup-0.1.5.dist-info/top_level.txt
cheerup-0.1.5.dist-info/RECORD
