Metadata-Version: 2.1
Name: cheerup
Version: 0.1.5
Summary: Cheer on your command-line expertise!
Author-email: Takashi Yamamiya <tak@metatoys.org>
Project-URL: Homepage, https://github.com/propella/cheerup
Project-URL: Bug Tracker, https://github.com/propella/cheerup/issues
Classifier: Programming Language :: Python :: 3
Classifier: License :: OSI Approved :: MIT License
Classifier: Operating System :: OS Independent
Requires-Python: >=3.10
License-File: LICENSE
Requires-Dist: openai
Requires-Dist: python-dotenv
Provides-Extra: dev
Requires-Dist: black ; extra == 'dev'
Requires-Dist: mypy ; extra == 'dev'
Requires-Dist: pylint ; extra == 'dev'
Requires-Dist: build ; extra == 'dev'
Requires-Dist: twine ; extra == 'dev'
